[
  {
    "path": "src/main/java/Duke.java",
    "fileType": "java",
    "lines": [
      {
        "lineNumber": 1,
        "author": {
          "gitId": "Tishya Khanna"
        },
        "content": "import java.util.Scanner;"
      },
      {
        "lineNumber": 2,
        "author": {
          "gitId": "-"
        },
        "content": "public class Duke {"
      },
      {
        "lineNumber": 3,
        "author": {
          "gitId": "Tishya Khanna"
        },
        "content": "    //Function spacer takes input string and converts it to be"
      },
      {
        "lineNumber": 4,
        "author": {
          "gitId": "Tishya Khanna"
        },
        "content": "    // printed with the appropriate lines and indentation"
      },
      {
        "lineNumber": 5,
        "author": {
          "gitId": "Tishya Khanna"
        },
        "content": "    private static void spacer(String input) {"
      },
      {
        "lineNumber": 6,
        "author": {
          "gitId": "Tishya Khanna"
        },
        "content": "        String separator \u003d \"    ____________________________________________________________\";"
      },
      {
        "lineNumber": 7,
        "author": {
          "gitId": "Tishya Khanna"
        },
        "content": "        String converted \u003d \"    \"  + input;"
      },
      {
        "lineNumber": 8,
        "author": {
          "gitId": "Tishya Khanna"
        },
        "content": "        System.out.println(separator);"
      },
      {
        "lineNumber": 9,
        "author": {
          "gitId": "Tishya Khanna"
        },
        "content": "        System.out.println(converted);"
      },
      {
        "lineNumber": 10,
        "author": {
          "gitId": "Tishya Khanna"
        },
        "content": "        System.out.println(separator + \"\\n\");"
      },
      {
        "lineNumber": 11,
        "author": {
          "gitId": "Tishya Khanna"
        },
        "content": ""
      },
      {
        "lineNumber": 12,
        "author": {
          "gitId": "Tishya Khanna"
        },
        "content": "    }"
      },
      {
        "lineNumber": 13,
        "author": {
          "gitId": "Tishya Khanna"
        },
        "content": ""
      },
      {
        "lineNumber": 14,
        "author": {
          "gitId": "-"
        },
        "content": "    public static void main(String[] args) {"
      },
      {
        "lineNumber": 15,
        "author": {
          "gitId": "-"
        },
        "content": "        String logo \u003d \" ____        _        \\n\""
      },
      {
        "lineNumber": 16,
        "author": {
          "gitId": "-"
        },
        "content": "                + \"|  _ \\\\ _   _| | _____ \\n\""
      },
      {
        "lineNumber": 17,
        "author": {
          "gitId": "-"
        },
        "content": "                + \"| | | | | | | |/ / _ \\\\\\n\""
      },
      {
        "lineNumber": 18,
        "author": {
          "gitId": "-"
        },
        "content": "                + \"| |_| | |_| |   \u003c  __/\\n\""
      },
      {
        "lineNumber": 19,
        "author": {
          "gitId": "-"
        },
        "content": "                + \"|____/ \\\\__,_|_|\\\\_\\\\___|\\n\";"
      },
      {
        "lineNumber": 20,
        "author": {
          "gitId": "Tishya Khanna"
        },
        "content": "        String start \u003d \"Hello! I\u0027m Duke\\n    What can I do for you?\";"
      },
      {
        "lineNumber": 21,
        "author": {
          "gitId": "Tishya Khanna"
        },
        "content": "        String end \u003d \"Bye. Hope to see you again soon!\";"
      },
      {
        "lineNumber": 22,
        "author": {
          "gitId": "Tishya Khanna"
        },
        "content": ""
      },
      {
        "lineNumber": 23,
        "author": {
          "gitId": "Tishya Khanna"
        },
        "content": "        TaskList myTaskList \u003d new TaskList(100);"
      },
      {
        "lineNumber": 24,
        "author": {
          "gitId": "Tishya Khanna"
        },
        "content": ""
      },
      {
        "lineNumber": 25,
        "author": {
          "gitId": "Tishya Khanna"
        },
        "content": "        spacer(start);"
      },
      {
        "lineNumber": 26,
        "author": {
          "gitId": "Tishya Khanna"
        },
        "content": ""
      },
      {
        "lineNumber": 27,
        "author": {
          "gitId": "Tishya Khanna"
        },
        "content": "        Scanner myInputReader \u003d new Scanner(System.in);"
      },
      {
        "lineNumber": 28,
        "author": {
          "gitId": "Tishya Khanna"
        },
        "content": "        String userInput \u003d myInputReader.nextLine();"
      },
      {
        "lineNumber": 29,
        "author": {
          "gitId": "Tishya Khanna"
        },
        "content": "        while(!userInput.equalsIgnoreCase(\"bye\")) {"
      },
      {
        "lineNumber": 30,
        "author": {
          "gitId": "Tishya Khanna"
        },
        "content": ""
      },
      {
        "lineNumber": 31,
        "author": {
          "gitId": "Tishya Khanna"
        },
        "content": "            if(userInput.equalsIgnoreCase(\"list\")) {"
      },
      {
        "lineNumber": 32,
        "author": {
          "gitId": "Tishya Khanna"
        },
        "content": "                myTaskList.printTasks();"
      },
      {
        "lineNumber": 33,
        "author": {
          "gitId": "Tishya Khanna"
        },
        "content": "            } else if(userInput.contains(\"done\")) {"
      },
      {
        "lineNumber": 34,
        "author": {
          "gitId": "Tishya Khanna"
        },
        "content": "                String[] numTasks \u003d userInput.split(\" \");"
      },
      {
        "lineNumber": 35,
        "author": {
          "gitId": "Tishya Khanna"
        },
        "content": "                String numberAsString \u003d numTasks[1];"
      },
      {
        "lineNumber": 36,
        "author": {
          "gitId": "Tishya Khanna"
        },
        "content": "                int number \u003d Integer.parseInt(numberAsString);"
      },
      {
        "lineNumber": 37,
        "author": {
          "gitId": "Tishya Khanna"
        },
        "content": "                spacer(myTaskList.taskDone(number));"
      },
      {
        "lineNumber": 38,
        "author": {
          "gitId": "Tishya Khanna"
        },
        "content": "            }"
      },
      {
        "lineNumber": 39,
        "author": {
          "gitId": "Tishya Khanna"
        },
        "content": "            else {"
      },
      {
        "lineNumber": 40,
        "author": {
          "gitId": "Tishya Khanna"
        },
        "content": "                myTaskList.addTasks(userInput);"
      },
      {
        "lineNumber": 41,
        "author": {
          "gitId": "Tishya Khanna"
        },
        "content": "            }"
      },
      {
        "lineNumber": 42,
        "author": {
          "gitId": "Tishya Khanna"
        },
        "content": "            userInput \u003d myInputReader.nextLine();"
      },
      {
        "lineNumber": 43,
        "author": {
          "gitId": "Tishya Khanna"
        },
        "content": "        }"
      },
      {
        "lineNumber": 44,
        "author": {
          "gitId": "Tishya Khanna"
        },
        "content": ""
      },
      {
        "lineNumber": 45,
        "author": {
          "gitId": "Tishya Khanna"
        },
        "content": "        spacer(end);"
      },
      {
        "lineNumber": 46,
        "author": {
          "gitId": "Tishya Khanna"
        },
        "content": ""
      },
      {
        "lineNumber": 47,
        "author": {
          "gitId": "-"
        },
        "content": "    }"
      },
      {
        "lineNumber": 48,
        "author": {
          "gitId": "Jeffry Lum"
        },
        "content": "}"
      }
    ],
    "authorContributionMap": {
      "Tishya Khanna": 39,
      "Jeffry Lum": 1,
      "-": 8
    }
  },
  {
    "path": "src/main/java/Task.java",
    "fileType": "java",
    "lines": [
      {
        "lineNumber": 1,
        "author": {
          "gitId": "Tishya Khanna"
        },
        "content": "public class Task {"
      },
      {
        "lineNumber": 2,
        "author": {
          "gitId": "Tishya Khanna"
        },
        "content": "    String name;"
      },
      {
        "lineNumber": 3,
        "author": {
          "gitId": "Tishya Khanna"
        },
        "content": "    boolean completed;"
      },
      {
        "lineNumber": 4,
        "author": {
          "gitId": "Tishya Khanna"
        },
        "content": ""
      },
      {
        "lineNumber": 5,
        "author": {
          "gitId": "Tishya Khanna"
        },
        "content": "    public Task(String taskInput) {"
      },
      {
        "lineNumber": 6,
        "author": {
          "gitId": "Tishya Khanna"
        },
        "content": "       name \u003d taskInput;"
      },
      {
        "lineNumber": 7,
        "author": {
          "gitId": "Tishya Khanna"
        },
        "content": "       completed \u003d false;"
      },
      {
        "lineNumber": 8,
        "author": {
          "gitId": "Tishya Khanna"
        },
        "content": "    }"
      },
      {
        "lineNumber": 9,
        "author": {
          "gitId": "Tishya Khanna"
        },
        "content": ""
      },
      {
        "lineNumber": 10,
        "author": {
          "gitId": "Tishya Khanna"
        },
        "content": "    public String taskComplete() {"
      },
      {
        "lineNumber": 11,
        "author": {
          "gitId": "Tishya Khanna"
        },
        "content": "        completed \u003d true;"
      },
      {
        "lineNumber": 12,
        "author": {
          "gitId": "Tishya Khanna"
        },
        "content": "        String firstLine \u003d \"Nice! I\u0027ve marked this task as done:\\n\";"
      },
      {
        "lineNumber": 13,
        "author": {
          "gitId": "Tishya Khanna"
        },
        "content": "        String secondLine \u003d \"      \" + this;"
      },
      {
        "lineNumber": 14,
        "author": {
          "gitId": "Tishya Khanna"
        },
        "content": ""
      },
      {
        "lineNumber": 15,
        "author": {
          "gitId": "Tishya Khanna"
        },
        "content": "        return firstLine+secondLine;"
      },
      {
        "lineNumber": 16,
        "author": {
          "gitId": "Tishya Khanna"
        },
        "content": "    }"
      },
      {
        "lineNumber": 17,
        "author": {
          "gitId": "Tishya Khanna"
        },
        "content": ""
      },
      {
        "lineNumber": 18,
        "author": {
          "gitId": "Tishya Khanna"
        },
        "content": "    @Override"
      },
      {
        "lineNumber": 19,
        "author": {
          "gitId": "Tishya Khanna"
        },
        "content": "    public String toString() {"
      },
      {
        "lineNumber": 20,
        "author": {
          "gitId": "Tishya Khanna"
        },
        "content": "        if(completed) {"
      },
      {
        "lineNumber": 21,
        "author": {
          "gitId": "Tishya Khanna"
        },
        "content": "          return \"[\\u2713] \" + name;"
      },
      {
        "lineNumber": 22,
        "author": {
          "gitId": "Tishya Khanna"
        },
        "content": "        } else {"
      },
      {
        "lineNumber": 23,
        "author": {
          "gitId": "Tishya Khanna"
        },
        "content": "            return \"[\\u2718] \" + name;"
      },
      {
        "lineNumber": 24,
        "author": {
          "gitId": "Tishya Khanna"
        },
        "content": "        }"
      },
      {
        "lineNumber": 25,
        "author": {
          "gitId": "Tishya Khanna"
        },
        "content": ""
      },
      {
        "lineNumber": 26,
        "author": {
          "gitId": "Tishya Khanna"
        },
        "content": "    }"
      },
      {
        "lineNumber": 27,
        "author": {
          "gitId": "Tishya Khanna"
        },
        "content": ""
      },
      {
        "lineNumber": 28,
        "author": {
          "gitId": "Tishya Khanna"
        },
        "content": ""
      },
      {
        "lineNumber": 29,
        "author": {
          "gitId": "Tishya Khanna"
        },
        "content": "}"
      }
    ],
    "authorContributionMap": {
      "Tishya Khanna": 29
    }
  },
  {
    "path": "src/main/java/TaskList.java",
    "fileType": "java",
    "lines": [
      {
        "lineNumber": 1,
        "author": {
          "gitId": "Tishya Khanna"
        },
        "content": "public class TaskList {"
      },
      {
        "lineNumber": 2,
        "author": {
          "gitId": "Tishya Khanna"
        },
        "content": "    Task[] myTaskList;"
      },
      {
        "lineNumber": 3,
        "author": {
          "gitId": "Tishya Khanna"
        },
        "content": "    int taskCount;"
      },
      {
        "lineNumber": 4,
        "author": {
          "gitId": "Tishya Khanna"
        },
        "content": ""
      },
      {
        "lineNumber": 5,
        "author": {
          "gitId": "Tishya Khanna"
        },
        "content": "    public TaskList(int numTasks) {"
      },
      {
        "lineNumber": 6,
        "author": {
          "gitId": "Tishya Khanna"
        },
        "content": "        myTaskList \u003d new Task[numTasks];"
      },
      {
        "lineNumber": 7,
        "author": {
          "gitId": "Tishya Khanna"
        },
        "content": "        taskCount \u003d 0;"
      },
      {
        "lineNumber": 8,
        "author": {
          "gitId": "Tishya Khanna"
        },
        "content": "    }"
      },
      {
        "lineNumber": 9,
        "author": {
          "gitId": "Tishya Khanna"
        },
        "content": ""
      },
      {
        "lineNumber": 10,
        "author": {
          "gitId": "Tishya Khanna"
        },
        "content": "    private static void spacerForTasks(String input) {"
      },
      {
        "lineNumber": 11,
        "author": {
          "gitId": "Tishya Khanna"
        },
        "content": "        String separator \u003d \"    ____________________________________________________________\";"
      },
      {
        "lineNumber": 12,
        "author": {
          "gitId": "Tishya Khanna"
        },
        "content": "        String converted \u003d \"    added: \"  + input;"
      },
      {
        "lineNumber": 13,
        "author": {
          "gitId": "Tishya Khanna"
        },
        "content": "        System.out.println(separator);"
      },
      {
        "lineNumber": 14,
        "author": {
          "gitId": "Tishya Khanna"
        },
        "content": "        System.out.println(converted);"
      },
      {
        "lineNumber": 15,
        "author": {
          "gitId": "Tishya Khanna"
        },
        "content": "        System.out.println(separator + \"\\n\");"
      },
      {
        "lineNumber": 16,
        "author": {
          "gitId": "Tishya Khanna"
        },
        "content": "    }"
      },
      {
        "lineNumber": 17,
        "author": {
          "gitId": "Tishya Khanna"
        },
        "content": ""
      },
      {
        "lineNumber": 18,
        "author": {
          "gitId": "Tishya Khanna"
        },
        "content": ""
      },
      {
        "lineNumber": 19,
        "author": {
          "gitId": "Tishya Khanna"
        },
        "content": "    public void addTasks(String addedTask) {"
      },
      {
        "lineNumber": 20,
        "author": {
          "gitId": "Tishya Khanna"
        },
        "content": "        taskCount++;"
      },
      {
        "lineNumber": 21,
        "author": {
          "gitId": "Tishya Khanna"
        },
        "content": "        myTaskList[taskCount] \u003d new Task(addedTask);"
      },
      {
        "lineNumber": 22,
        "author": {
          "gitId": "Tishya Khanna"
        },
        "content": "        spacerForTasks(addedTask);"
      },
      {
        "lineNumber": 23,
        "author": {
          "gitId": "Tishya Khanna"
        },
        "content": "    }"
      },
      {
        "lineNumber": 24,
        "author": {
          "gitId": "Tishya Khanna"
        },
        "content": ""
      },
      {
        "lineNumber": 25,
        "author": {
          "gitId": "Tishya Khanna"
        },
        "content": "    public void printTasks() {"
      },
      {
        "lineNumber": 26,
        "author": {
          "gitId": "Tishya Khanna"
        },
        "content": "        String separator \u003d \"    ____________________________________________________________\";"
      },
      {
        "lineNumber": 27,
        "author": {
          "gitId": "Tishya Khanna"
        },
        "content": "        System.out.println(separator);"
      },
      {
        "lineNumber": 28,
        "author": {
          "gitId": "Tishya Khanna"
        },
        "content": "        System.out.println(\"    Here are the tasks in your list:\");"
      },
      {
        "lineNumber": 29,
        "author": {
          "gitId": "Tishya Khanna"
        },
        "content": "        for(int i \u003d 1; i \u003c\u003dtaskCount; i ++) {"
      },
      {
        "lineNumber": 30,
        "author": {
          "gitId": "Tishya Khanna"
        },
        "content": "            System.out.println(\"    \" + i + \".\" + myTaskList[i]);"
      },
      {
        "lineNumber": 31,
        "author": {
          "gitId": "Tishya Khanna"
        },
        "content": "        }"
      },
      {
        "lineNumber": 32,
        "author": {
          "gitId": "Tishya Khanna"
        },
        "content": "        System.out.println(separator + \"\\n\");"
      },
      {
        "lineNumber": 33,
        "author": {
          "gitId": "Tishya Khanna"
        },
        "content": ""
      },
      {
        "lineNumber": 34,
        "author": {
          "gitId": "Tishya Khanna"
        },
        "content": "    }"
      },
      {
        "lineNumber": 35,
        "author": {
          "gitId": "Tishya Khanna"
        },
        "content": ""
      },
      {
        "lineNumber": 36,
        "author": {
          "gitId": "Tishya Khanna"
        },
        "content": "    public String taskDone(int index) {"
      },
      {
        "lineNumber": 37,
        "author": {
          "gitId": "Tishya Khanna"
        },
        "content": "       return myTaskList[index].taskComplete();"
      },
      {
        "lineNumber": 38,
        "author": {
          "gitId": "Tishya Khanna"
        },
        "content": "    }"
      },
      {
        "lineNumber": 39,
        "author": {
          "gitId": "Tishya Khanna"
        },
        "content": "}"
      }
    ],
    "authorContributionMap": {
      "Tishya Khanna": 39
    }
  },
  {
    "path": "src/main/java/Tasks.java",
    "fileType": "java",
    "lines": [
      {
        "lineNumber": 1,
        "author": {
          "gitId": "Tishya Khanna"
        },
        "content": "public class Tasks {"
      },
      {
        "lineNumber": 2,
        "author": {
          "gitId": "Tishya Khanna"
        },
        "content": "    String[] myTaskList;"
      },
      {
        "lineNumber": 3,
        "author": {
          "gitId": "Tishya Khanna"
        },
        "content": "    int taskCount;"
      },
      {
        "lineNumber": 4,
        "author": {
          "gitId": "Tishya Khanna"
        },
        "content": ""
      },
      {
        "lineNumber": 5,
        "author": {
          "gitId": "Tishya Khanna"
        },
        "content": "    public Tasks(int numTasks) {"
      },
      {
        "lineNumber": 6,
        "author": {
          "gitId": "Tishya Khanna"
        },
        "content": "        myTaskList \u003d new String[numTasks];"
      },
      {
        "lineNumber": 7,
        "author": {
          "gitId": "Tishya Khanna"
        },
        "content": "        taskCount \u003d 1;"
      },
      {
        "lineNumber": 8,
        "author": {
          "gitId": "Tishya Khanna"
        },
        "content": "    }"
      },
      {
        "lineNumber": 9,
        "author": {
          "gitId": "Tishya Khanna"
        },
        "content": ""
      },
      {
        "lineNumber": 10,
        "author": {
          "gitId": "Tishya Khanna"
        },
        "content": "    private static void spacerForTasks(String input) {"
      },
      {
        "lineNumber": 11,
        "author": {
          "gitId": "Tishya Khanna"
        },
        "content": "        String separator \u003d \"    ____________________________________________________________\";"
      },
      {
        "lineNumber": 12,
        "author": {
          "gitId": "Tishya Khanna"
        },
        "content": "        String converted \u003d \"    added: \"  + input;"
      },
      {
        "lineNumber": 13,
        "author": {
          "gitId": "Tishya Khanna"
        },
        "content": "        System.out.println(separator);"
      },
      {
        "lineNumber": 14,
        "author": {
          "gitId": "Tishya Khanna"
        },
        "content": "        System.out.println(converted);"
      },
      {
        "lineNumber": 15,
        "author": {
          "gitId": "Tishya Khanna"
        },
        "content": "        System.out.println(separator + \"\\n\");"
      },
      {
        "lineNumber": 16,
        "author": {
          "gitId": "Tishya Khanna"
        },
        "content": "    }"
      },
      {
        "lineNumber": 17,
        "author": {
          "gitId": "Tishya Khanna"
        },
        "content": ""
      },
      {
        "lineNumber": 18,
        "author": {
          "gitId": "Tishya Khanna"
        },
        "content": ""
      },
      {
        "lineNumber": 19,
        "author": {
          "gitId": "Tishya Khanna"
        },
        "content": "    public void addTasks(String addedTask) {"
      },
      {
        "lineNumber": 20,
        "author": {
          "gitId": "Tishya Khanna"
        },
        "content": "        taskCount++;"
      },
      {
        "lineNumber": 21,
        "author": {
          "gitId": "Tishya Khanna"
        },
        "content": "        myTaskList[taskCount] \u003d addedTask;"
      },
      {
        "lineNumber": 22,
        "author": {
          "gitId": "Tishya Khanna"
        },
        "content": "        spacerForTasks(addedTask);"
      },
      {
        "lineNumber": 23,
        "author": {
          "gitId": "Tishya Khanna"
        },
        "content": "    }"
      },
      {
        "lineNumber": 24,
        "author": {
          "gitId": "Tishya Khanna"
        },
        "content": ""
      },
      {
        "lineNumber": 25,
        "author": {
          "gitId": "Tishya Khanna"
        },
        "content": "    public void printTasks() {"
      },
      {
        "lineNumber": 26,
        "author": {
          "gitId": "Tishya Khanna"
        },
        "content": "        String separator \u003d \"    ____________________________________________________________\";"
      },
      {
        "lineNumber": 27,
        "author": {
          "gitId": "Tishya Khanna"
        },
        "content": "        System.out.println(separator);"
      },
      {
        "lineNumber": 28,
        "author": {
          "gitId": "Tishya Khanna"
        },
        "content": "        for(int i \u003d 1; i \u003c\u003dtaskCount; i ++) {"
      },
      {
        "lineNumber": 29,
        "author": {
          "gitId": "Tishya Khanna"
        },
        "content": "            System.out.println(\"    \" + i + \": \" + myTaskList[i]);"
      },
      {
        "lineNumber": 30,
        "author": {
          "gitId": "Tishya Khanna"
        },
        "content": "        }"
      },
      {
        "lineNumber": 31,
        "author": {
          "gitId": "Tishya Khanna"
        },
        "content": "        System.out.println(separator + \"\\n\");"
      },
      {
        "lineNumber": 32,
        "author": {
          "gitId": "Tishya Khanna"
        },
        "content": ""
      },
      {
        "lineNumber": 33,
        "author": {
          "gitId": "Tishya Khanna"
        },
        "content": "    }"
      },
      {
        "lineNumber": 34,
        "author": {
          "gitId": "Tishya Khanna"
        },
        "content": "}"
      }
    ],
    "authorContributionMap": {
      "Tishya Khanna": 34
    }
  }
]
