{
  "authorDailyContributionsMap": {
    "gabrielseow": [
      {
        "insertions": 72,
        "deletions": 2,
        "date": "2019-08-22",
        "commitResults": [
          {
            "hash": "6df40549cf7998d7e5ba7ddfa3405be9389c32c6",
            "messageTitle": "level one complete",
            "messageBody": "",
            "insertions": 45,
            "deletions": 1
          },
          {
            "hash": "441bb2d91abfae8cb60d0b9eff2450ac7e21358a",
            "messageTitle": "level one complete",
            "messageBody": "",
            "insertions": 0,
            "deletions": 1
          },
          {
            "hash": "0f21e4a36d3063b8fadd8cf2bafb70231f78a94e",
            "messageTitle": "level two complete",
            "messageBody": "",
            "insertions": 27,
            "deletions": 0
          }
        ]
      },
      {
        "insertions": 45,
        "deletions": 10,
        "date": "2019-08-23",
        "commitResults": [
          {
            "hash": "cefac209c72a91d49fd489c3fcdc7d084ef9b0bc",
            "messageTitle": "level three complete",
            "messageBody": "",
            "insertions": 45,
            "deletions": 10
          }
        ]
      },
      {
        "insertions": 196,
        "deletions": 40,
        "date": "2019-08-28",
        "commitResults": [
          {
            "hash": "97147a421179230d221b931ecfdeb2619edb91cc",
            "messageTitle": "level four complete",
            "messageBody": "",
            "insertions": 196,
            "deletions": 40
          }
        ]
      },
      {
        "insertions": 74,
        "deletions": 43,
        "date": "2019-08-30",
        "commitResults": [
          {
            "hash": "d064d09ee0fc23dbd1770b5f276e23d722a97a20",
            "messageTitle": "level 5 complete",
            "messageBody": "",
            "insertions": 74,
            "deletions": 43
          }
        ]
      }
    ]
  },
  "authorFinalContributionMap": {
    "gabrielseow": 292
  },
  "authorFileTypeContributionMap": {
    "gabrielseow": {
      "java": 292,
      "md": 0,
      "fxml": 0,
      "sh": 0,
      "bat": 0,
      "gradle": 0,
      "txt": 0
    }
  },
  "authorContributionVariance": {
    "gabrielseow": 4159.849
  },
  "authorDisplayNameMap": {
    "gabrielseow": "SEOW .. RIEL"
  }
}
