{
  "authorDailyContributionsMap": {
    "yyuanxin": [
      {
        "insertions": 259,
        "deletions": 71,
        "date": "2019-08-20",
        "commitResults": [
          {
            "hash": "317458dc9e02eab73e058d20ea7c13196e8eb63e",
            "messageTitle": "greet, echo, exit",
            "messageBody": "",
            "insertions": 16,
            "deletions": 6
          },
          {
            "hash": "2280c784e1a863990ba389c274c2452226840631",
            "messageTitle": "add, lists",
            "messageBody": "",
            "insertions": 16,
            "deletions": 3
          },
          {
            "hash": "248f3a905754da2aed5c55d216dbc909736fad16",
            "messageTitle": "mark as done",
            "messageBody": "",
            "insertions": 39,
            "deletions": 3
          },
          {
            "hash": "21b72d859925430d80254940af0bc9d30305956f",
            "messageTitle": "todos, events, deadlines",
            "messageBody": "",
            "insertions": 84,
            "deletions": 16
          },
          {
            "hash": "0f63a9a8f4a1978bca53f251814573d4eb867dcb",
            "messageTitle": "handle errors",
            "messageBody": "",
            "insertions": 72,
            "deletions": 37
          },
          {
            "hash": "e0d2c2c63ad476eaa293c4386af005d0d50b4196",
            "messageTitle": "delete",
            "messageBody": "",
            "insertions": 32,
            "deletions": 6
          }
        ]
      },
      {
        "insertions": 986,
        "deletions": 294,
        "date": "2019-08-28",
        "commitResults": [
          {
            "hash": "abb86b4e147629f6c21adc7a11e76e060f46867a",
            "messageTitle": "save",
            "messageBody": "",
            "insertions": 157,
            "deletions": 2
          },
          {
            "hash": "2ae29135f5f45d18d9320a74ee650e0e8143d6d8",
            "messageTitle": "dates and times",
            "messageBody": "",
            "insertions": 191,
            "deletions": 3
          },
          {
            "hash": "f829d580b2c4c50fede43d8bdc1c8852f45ba734",
            "messageTitle": "More OOP",
            "messageBody": "",
            "insertions": 508,
            "deletions": 284
          },
          {
            "hash": "446496cd8ab289da51029eb5b6cd3369cca61f23",
            "messageTitle": "JUnit testing",
            "messageBody": "",
            "insertions": 38,
            "deletions": 2
          },
          {
            "hash": "4726fb88e1db60deeb095c5ac21c07069c5205fb",
            "messageTitle": "javadoc",
            "messageBody": "",
            "insertions": 41,
            "deletions": 1
          },
          {
            "hash": "adc3ec09703dd40e420398930a04b70f36a3fc90",
            "messageTitle": "find tasks",
            "messageBody": "",
            "insertions": 49,
            "deletions": 2
          },
          {
            "hash": "e51e561454b4f6a2d9efef4596641c9d18891e33",
            "messageTitle": "coding standards",
            "messageBody": "",
            "insertions": 2,
            "deletions": 0
          }
        ]
      },
      {
        "insertions": 67,
        "deletions": 2,
        "date": "2019-09-02",
        "commitResults": [
          {
            "hash": "4e1a704bddde303c6e31cc4624f65dfc56d82d7b",
            "messageTitle": "organize classes into java packages",
            "messageBody": "",
            "insertions": 67,
            "deletions": 2
          }
        ]
      },
      {
        "insertions": 604,
        "deletions": 170,
        "date": "2019-09-04",
        "commitResults": [
          {
            "hash": "1df4ae36fb61944cc9629bcbfbdab96217ad501d",
            "messageTitle": "update gradle - more test cases added",
            "messageBody": "",
            "insertions": 75,
            "deletions": 9
          },
          {
            "hash": "598fe3d329240e3da7f17882ce467e4872c88af4",
            "messageTitle": "added checkstyle",
            "messageBody": "",
            "insertions": 257,
            "deletions": 84
          },
          {
            "hash": "a075ce59cc39dbb78714c6b04732de9fbd93b56e",
            "messageTitle": "GUI",
            "messageBody": "",
            "insertions": 272,
            "deletions": 77
          }
        ]
      },
      {
        "insertions": 201,
        "deletions": 136,
        "date": "2019-09-09",
        "commitResults": [
          {
            "hash": "efde579248153b6857e7e8b3d5efe82a719f056d",
            "messageTitle": "Add assertions in methods",
            "messageBody": "",
            "insertions": 9,
            "deletions": 1
          },
          {
            "hash": "f36a512f21425d87787ad06bdc948a98238f1e63",
            "messageTitle": "Improve Code Quality with JavaDocs and refactor codes",
            "messageBody": "Add and Modify JavaDocs to align to coding standards\nReplace some \"if\" statements to \"switch\" block\nMake Parser Methods to static\n",
            "insertions": 192,
            "deletions": 135
          }
        ]
      },
      {
        "insertions": 196,
        "deletions": 2,
        "date": "2019-09-11",
        "commitResults": [
          {
            "hash": "c717727ffbac4e506f60ed7d3c4be091a6cdb80d",
            "messageTitle": "Implement friendlier syntax extension",
            "messageBody": "Allow users to define their own aliases\n",
            "insertions": 196,
            "deletions": 2
          }
        ]
      },
      {
        "insertions": 236,
        "deletions": 66,
        "date": "2019-09-16",
        "commitResults": [
          {
            "hash": "ba125ca8fbd1049d01a0b15f3a12d8c1364142a6",
            "messageTitle": "Improve GUI appearance Add JavaFX CSS StyleSheet",
            "messageBody": "",
            "insertions": 64,
            "deletions": 60
          },
          {
            "hash": "1df8128d09e9e37ea767b481c8b72aa4729e3aee",
            "messageTitle": "Add User Guide",
            "messageBody": "Update README.md",
            "insertions": 172,
            "deletions": 6
          }
        ]
      },
      {
        "insertions": 95,
        "deletions": 15,
        "date": "2019-09-18",
        "commitResults": [
          {
            "hash": "6338e13cb9c5398a864418128282783359e3727b",
            "messageTitle": "Add jar file for product release Add shadowJar plugin to build.gradle Add check for file does not exist in Alias class Generalize text files directory for .jar release to work",
            "messageBody": "",
            "insertions": 75,
            "deletions": 8
          },
          {
            "hash": "640448d1289ba1b3b3ffc9967c06659006d19493",
            "messageTitle": "Add cross-platform support",
            "messageBody": "",
            "insertions": 20,
            "deletions": 7
          }
        ]
      },
      {
        "insertions": 131,
        "deletions": 75,
        "date": "2019-09-22",
        "commitResults": [
          {
            "hash": "1c35abe27eae00aa278ebf29a3a13202b6567579",
            "messageTitle": "Fix Checkstyle error Separate test cases into specific test classes",
            "messageBody": "",
            "insertions": 131,
            "deletions": 75
          }
        ]
      },
      {
        "insertions": 213,
        "deletions": 194,
        "date": "2019-09-23",
        "commitResults": [
          {
            "hash": "957c130009cf4df61db4506b0c2e83fd0bb8783d",
            "messageTitle": "add full window resizing package files to organize",
            "messageBody": "",
            "insertions": 119,
            "deletions": 125
          },
          {
            "hash": "8cbd8e1f7b48f67cfdffec2286c6cd031fd6dbc5",
            "messageTitle": "Fix missing minutes of date time Add more helpful error messages",
            "messageBody": "",
            "insertions": 10,
            "deletions": 6
          },
          {
            "hash": "094d09afe68841eea152c08c2f5352e620f32b9f",
            "messageTitle": "Update User Guide",
            "messageBody": "",
            "insertions": 7,
            "deletions": 7
          },
          {
            "hash": "a71a78bcf77c0075411424908959ffbe204787f5",
            "messageTitle": "Improve code to update text file Fix unable to overwrite bye command alias issue.",
            "messageBody": "",
            "insertions": 29,
            "deletions": 36
          },
          {
            "hash": "c6f732420acfe1c25472d4a270ec3c8dd0d3b2c3",
            "messageTitle": "Add introduction and get started in user guide",
            "messageBody": "",
            "insertions": 37,
            "deletions": 9
          },
          {
            "hash": "d28032121c047229bc2709b250f910a32003d1ad",
            "messageTitle": "Fix typo in exception message",
            "messageBody": "",
            "insertions": 1,
            "deletions": 1
          },
          {
            "hash": "0c7f516defbdbdb5a1c11165beb93e4165b80499",
            "messageTitle": "Update User Guide",
            "messageBody": "",
            "insertions": 1,
            "deletions": 0
          },
          {
            "hash": "235ea3e874fcb9293afe7d6ebe51e1c23a1f43f8",
            "messageTitle": "Fix overwrite alias in wrong order issue",
            "messageBody": "",
            "insertions": 9,
            "deletions": 10
          }
        ]
      }
    ]
  },
  "authorFinalContributionMap": {
    "yyuanxin": 1828
  },
  "authorFileTypeContributionMap": {
    "yyuanxin": {
      "java": 1531,
      "md": 200,
      "fxml": 40,
      "sh": 0,
      "bat": 0,
      "gradle": 47,
      "txt": 10
    }
  },
  "authorContributionVariance": {
    "yyuanxin": 61599.293
  },
  "authorDisplayNameMap": {
    "yyuanxin": "CS2103T-T10-2 YEO Y ... N XIN"
  }
}
