{
  "authorDailyContributionsMap": {
    "Jeffry Lum": [],
    "Khairul": [
      {
        "insertions": 42,
        "deletions": 14,
        "date": "2019-08-18",
        "commitResults": [
          {
            "hash": "29ffe1bb5c8bcb72c6715e1c5ab8bdcf59f16d92",
            "messageTitle": "Level 1",
            "messageBody": "",
            "insertions": 19,
            "deletions": 6
          },
          {
            "hash": "761780fc1eaf90a103acaa7cf275c6059bca516e",
            "messageTitle": "Level 2",
            "messageBody": "",
            "insertions": 23,
            "deletions": 8
          }
        ]
      }
    ]
  },
  "authorFinalContributionMap": {
    "Jeffry Lum": 1,
    "Khairul": 28
  },
  "authorFileTypeContributionMap": {
    "Jeffry Lum": {
      "java": 1,
      "md": 0,
      "fxml": 0,
      "sh": 0,
      "bat": 0,
      "gradle": 0,
      "txt": 0
    },
    "Khairul": {
      "java": 28,
      "md": 0,
      "fxml": 0,
      "sh": 0,
      "bat": 0,
      "gradle": 0,
      "txt": 0
    }
  },
  "authorContributionVariance": {
    "Jeffry Lum": 0.0,
    "Khairul": 696.8889
  },
  "authorDisplayNameMap": {
    "Jeffry Lum": "Jeffry Lum",
    "Khairul": "Khairul"
  }
}
